.gitignore
Changelog.md
README.rst
setup.py
picu/__init__.py
picu/constants.py
picu/exceptions.py
picu/finalize.py
picu/loader.py
picu/utils.py
picu.egg-info/PKG-INFO
picu.egg-info/SOURCES.txt
picu.egg-info/dependency_links.txt
picu.egg-info/top_level.txt