Metadata-Version: 2.1
Name: picu
Version: 1.6
Summary: Python ctypes-based ICU Wrapper
Home-page: UNKNOWN
Author: Wil Tan, Cofomo and Viagénie
Author-email: wil@cloudregistry.net
License: MIT/X
Platform: UNKNOWN
